snakemake_software_deployment_plugin_envmodules/__init__.py
snakemake_software_deployment_plugin_envmodules-0.1.5.dist-info/METADATA
snakemake_software_deployment_plugin_envmodules-0.1.5.dist-info/WHEEL
snakemake_software_deployment_plugin_envmodules-0.1.5.dist-info/RECORD
