Metadata-Version: 2.4
Name: snakemake-software-deployment-plugin-envmodules
Version: 0.1.5
Summary: Software deployment plugin for Snakemake using environment modules.
Project-URL: repository, https://github.com/snakemake/snakemake-software-deployment-plugin-envmodules
Project-URL: documentation, https://snakemake.github.io/snakemake-plugin-catalog/plugins/software-deployment/envmodules.html
Author-email: Johannes Köster <johannes.koester@uni-due.de>
Requires-Python: <4.0,>=3.11
Requires-Dist: snakemake-interface-common<2.0.0,>=1.17.4
Requires-Dist: snakemake-interface-software-deployment-plugins<1.0,>=0.8.0
